[
  {
    "Type": "BodySetup",
    "Name": "BodySetup_0",
    "Outer": "SM_pal_b00grass_Lodenfel_Debris_Floor_05",
    "Class": "UScriptClass'BodySetup'",
    "Properties": {
      "PhysMaterial": {
        "ObjectName": "PhysicalMaterial'PM_Pal_Stone'",
        "ObjectPath": "Pal/Content/Pal/Material/PhysicsMaterial/PM_Pal_Stone.0"
      },
      "DefaultInstance": {
        "ObjectType": "ECollisionChannel::ECC_WorldStatic",
        "CollisionProfileName": "Background",
        "CollisionResponses": {
          "ResponseArray": [
            {
              "Channel": "Attack",
              "Response": "ECollisionResponse::ECR_Block"
            },
            {
              "Channel": "SystemVolume",
              "Response": "ECollisionResponse::ECR_Ignore"
            },
            {
              "Channel": "LiftedupPawn",
              "Response": "ECollisionResponse::ECR_Block"
            },
            {
              "Channel": "AISightRayCast",
              "Response": "ECollisionResponse::ECR_Block"
            },
            {
              "Channel": "vsGroundRayCast",
              "Response": "ECollisionResponse::ECR_Block"
            },
            {
              "Channel": "ClimbRayCast",
              "Response": "ECollisionResponse::ECR_Block"
            },
            {
              "Channel": "RollingRayCast",
              "Response": "ECollisionResponse::ECR_Block"
            }
          ]
        }
      }
    },
    "BodySetupGuid": "CFB85CB54214363EB6F189A355909D00",
    "CookedFormatData": {
      "PhysXPC": {
        "BulkDataFlags": "BULKDATA_SingleUse | BULKDATA_ForceInlinePayload",
        "ElementCount": 50034,
        "SizeOnDisk": 50034,
        "OffsetInFile": "0x1B788"
      }
    }
  },
  {
    "Type": "NavCollision",
    "Name": "NavCollision_0",
    "Outer": "SM_pal_b00grass_Lodenfel_Debris_Floor_05",
    "Class": "UScriptClass'NavCollision'",
    "CookedFormatData": {
      "NavCollision_Chaos": {
        "BulkDataFlags": "BULKDATA_SingleUse | BULKDATA_ForceInlinePayload",
        "ElementCount": 21,
        "SizeOnDisk": 21,
        "OffsetInFile": "0x27B3C"
      }
    }
  },
  {
    "Type": "StaticMesh",
    "Name": "SM_pal_b00grass_Lodenfel_Debris_Floor_05",
    "Class": "UScriptClass'StaticMesh'",
    "Properties": {
      "StaticMaterials": [
        {
          "MaterialInterface": {
            "ObjectName": "MaterialInstanceConstant'MI_pal_b00_Lordenfel_Floor_Bricks_01'",
            "ObjectPath": "Pal/Content/Pal/Model/Stage/b00/Lordenfel/Materials/MI_pal_b00_Lordenfel_Floor_Bricks_01.0"
          },
          "MaterialSlotName": "MI_Floor_Bricks_01",
          "ImportedMaterialSlotName": "MI_Floor_Bricks_01",
          "UVChannelData": {
            "bInitialized": true,
            "bOverrideDensities": false,
            "LocalUVDensities": 375.8325,
            "LocalUVDensities": 584.8498,
            "LocalUVDensities": 0.0,
            "LocalUVDensities": 0.0
          }
        }
      ],
      "LightmapUVDensity": 584.8498,
      "LightMapResolution": 64,
      "LightMapCoordinateIndex": 1,
      "ExtendedBounds": {
        "Origin": {
          "X": -3.0107422,
          "Y": -7.471756,
          "Z": 10.422323
        },
        "BoxExtent": {
          "X": 139.60449,
          "Y": 158.50154,
          "Z": 21.718954
        },
        "SphereRadius": 175.4699249267578
      }
    },
    "BodySetup": {
      "ObjectName": "BodySetup'SM_pal_b00grass_Lodenfel_Debris_Floor_05:BodySetup_0'",
      "ObjectPath": "Pal/Content/Pal/Model/Stage/b00/Lordenfel/Meshes/Architecture/Floors/SM_pal_b00grass_Lodenfel_Debris_Floor_05.0"
    },
    "NavCollision": {
      "ObjectName": "NavCollision'SM_pal_b00grass_Lodenfel_Debris_Floor_05:NavCollision_0'",
      "ObjectPath": "Pal/Content/Pal/Model/Stage/b00/Lordenfel/Meshes/Architecture/Floors/SM_pal_b00grass_Lodenfel_Debris_Floor_05.1"
    },
    "LightingGuid": "AAB4F05B-4220930F-BB7F8F99-396E121C",
    "RenderData": {
      "LODs": [
        {
          "Sections": [
            {
              "MaterialIndex": 0,
              "FirstIndex": 0,
              "NumTriangles": 348,
              "MinVertexIndex": 0,
              "MaxVertexIndex": 489,
              "bEnableCollision": true,
              "bCastShadow": true,
              "bForceOpaque": false,
              "bVisibleInRayTracing": true
            }
          ],
          "MaxDeviation": 21.696201,
          "PositionVertexBuffer": {
            "Stride": 12,
            "NumVertices": 490
          },
          "VertexBuffer": {
            "NumTexCoords": 2,
            "NumVertices": 490,
            "Strides": -1,
            "UseHighPrecisionTangentBasis": false,
            "UseFullPrecisionUVs": false
          },
          "ColorVertexBuffer": {
            "Stride": 0,
            "NumVertices": 0
          },
          "CardRepresentationData": {
            "Bounds": {
              "Min": {
                "X": -143.61523,
                "Y": -166.9733,
                "Z": -12.296631
              },
              "Max": {
                "X": 137.59375,
                "Y": 152.02979,
                "Z": 33.141277
              },
              "IsValid": 1
            },
            "MaxLodLevel": 0,
            "bMostlyTwoSided": false,
            "CardBuildData": [
              {
                "OBB": {
                  "AxisX": {
                    "X": 0.0,
                    "Y": 1.0,
                    "Z": 0.0
                  },
                  "AxisY": {
                    "X": 0.0,
                    "Y": 0.0,
                    "Z": 1.0
                  },
                  "AxisZ": {
                    "X": -1.0,
                    "Y": 0.0,
                    "Z": 0.0
                  },
                  "Origin": {
                    "X": -38.010742,
                    "Y": -2.720993,
                    "Z": 10.422323
                  },
                  "Extent": {
                    "X": 154.75076,
                    "Y": 22.718956,
                    "Z": 110.0
                  }
                },
                "LODLevel": 0,
                "AxisAlignedDirectionIndex": 0
              },
              {
                "OBB": {
                  "AxisX": {
                    "X": 0.0,
                    "Y": 1.0,
                    "Z": 0.0
                  },
                  "AxisY": {
                    "X": 0.0,
                    "Y": 0.0,
                    "Z": 1.0
                  },
                  "AxisZ": {
                    "X": -1.0,
                    "Y": 0.0,
                    "Z": 0.0
                  },
                  "Origin": {
                    "X": 56.989258,
                    "Y": -32.471756,
                    "Z": 14.281801
                  },
                  "Extent": {
                    "X": 95.0,
                    "Y": 18.859478,
                    "Z": 35.0
                  }
                },
                "LODLevel": 0,
                "AxisAlignedDirectionIndex": 0
              },
              {
                "OBB": {
                  "AxisX": {
                    "X": 0.0,
                    "Y": 1.0,
                    "Z": 0.0
                  },
                  "AxisY": {
                    "X": 0.0,
                    "Y": 0.0,
                    "Z": 1.0
                  },
                  "AxisZ": {
                    "X": 1.0,
                    "Y": 0.0,
                    "Z": 0.0
                  },
                  "Origin": {
                    "X": 16.989258,
                    "Y": -7.471756,
                    "Z": 10.422323
                  },
                  "Extent": {
                    "X": 159.50153,
                    "Y": 22.718956,
                    "Z": 125.0
                  }
                },
                "LODLevel": 0,
                "AxisAlignedDirectionIndex": 1
              },
              {
                "OBB": {
                  "AxisX": {
                    "X": 0.0,
                    "Y": 1.0,
                    "Z": 0.0
                  },
                  "AxisY": {
                    "X": 0.0,
                    "Y": 0.0,
                    "Z": 1.0
                  },
                  "AxisZ": {
                    "X": 1.0,
                    "Y": 0.0,
                    "Z": 0.0
                  },
                  "Origin": {
                    "X": -18.010742,
                    "Y": -2.471756,
                    "Z": 14.281801
                  },
                  "Extent": {
                    "X": 115.0,
                    "Y": 18.859478,
                    "Z": 50.0
                  }
                },
                "LODLevel": 0,
                "AxisAlignedDirectionIndex": 1
              },
              {
                "OBB": {
                  "AxisX": {
                    "X": 1.0,
                    "Y": 0.0,
                    "Z": 0.0
                  },
                  "AxisY": {
                    "X": 0.0,
                    "Y": 0.0,
                    "Z": 1.0
                  },
                  "AxisZ": {
                    "X": 0.0,
                    "Y": -1.0,
                    "Z": 0.0
                  },
                  "Origin": {
                    "X": -3.0107422,
                    "Y": -47.471756,
                    "Z": 10.422323
                  },
                  "Extent": {
                    "X": 140.0,
                    "Y": 22.718956,
                    "Z": 125.0
                  }
                },
                "LODLevel": 0,
                "AxisAlignedDirectionIndex": 2
              },
              {
                "OBB": {
                  "AxisX": {
                    "X": 1.0,
                    "Y": 0.0,
                    "Z": 0.0
                  },
                  "AxisY": {
                    "X": 0.0,
                    "Y": 0.0,
                    "Z": 1.0
                  },
                  "AxisZ": {
                    "X": 0.0,
                    "Y": -1.0,
                    "Z": 0.0
                  },
                  "Origin": {
                    "X": -3.0107422,
                    "Y": 62.528244,
                    "Z": 14.281801
                  },
                  "Extent": {
                    "X": 120.0,
                    "Y": 18.859478,
                    "Z": 55.0
                  }
                },
                "LODLevel": 0,
                "AxisAlignedDirectionIndex": 2
              },
              {
                "OBB": {
                  "AxisX": {
                    "X": 1.0,
                    "Y": 0.0,
                    "Z": 0.0
                  },
                  "AxisY": {
                    "X": 0.0,
                    "Y": 0.0,
                    "Z": 1.0
                  },
                  "AxisZ": {
                    "X": 0.0,
                    "Y": -1.0,
                    "Z": 0.0
                  },
                  "Origin": {
                    "X": 1.9892578,
                    "Y": -42.471756,
                    "Z": 14.281801
                  },
                  "Extent": {
                    "X": 95.0,
                    "Y": 18.859478,
                    "Z": 30.0
                  }
                },
                "LODLevel": 0,
                "AxisAlignedDirectionIndex": 2
              },
              {
                "OBB": {
                  "AxisX": {
                    "X": 1.0,
                    "Y": 0.0,
                    "Z": 0.0
                  },
                  "AxisY": {
                    "X": 0.0,
                    "Y": 0.0,
                    "Z": 1.0
                  },
                  "AxisZ": {
                    "X": 0.0,
                    "Y": 1.0,
                    "Z": 0.0
                  },
                  "Origin": {
                    "X": -3.0107422,
                    "Y": 32.528244,
                    "Z": 10.422323
                  },
                  "Extent": {
                    "X": 140.0,
                    "Y": 22.718956,
                    "Z": 125.0
                  }
                },
                "LODLevel": 0,
                "AxisAlignedDirectionIndex": 3
              },
              {
                "OBB": {
                  "AxisX": {
                    "X": 1.0,
                    "Y": 0.0,
                    "Z": 0.0
                  },
                  "AxisY": {
                    "X": 0.0,
                    "Y": 0.0,
                    "Z": 1.0
                  },
                  "AxisZ": {
                    "X": 0.0,
                    "Y": 1.0,
                    "Z": 0.0
                  },
                  "Origin": {
                    "X": -3.0107422,
                    "Y": -47.471756,
                    "Z": 14.281801
                  },
                  "Extent": {
                    "X": 120.0,
                    "Y": 18.859478,
                    "Z": 45.0
                  }
                },
                "LODLevel": 0,
                "AxisAlignedDirectionIndex": 3
              },
              {
                "OBB": {
                  "AxisX": {
                    "X": 1.0,
                    "Y": 0.0,
                    "Z": 0.0
                  },
                  "AxisY": {
                    "X": 0.0,
                    "Y": 0.0,
                    "Z": 1.0
                  },
                  "AxisZ": {
                    "X": 0.0,
                    "Y": 1.0,
                    "Z": 0.0
                  },
                  "Origin": {
                    "X": 1.9892578,
                    "Y": -97.471756,
                    "Z": 14.281801
                  },
                  "Extent": {
                    "X": 95.0,
                    "Y": 18.859478,
                    "Z": 35.0
                  }
                },
                "LODLevel": 0,
                "AxisAlignedDirectionIndex": 3
              },
              {
                "OBB": {
                  "AxisX": {
                    "X": 1.0,
                    "Y": 0.0,
                    "Z": 0.0
                  },
                  "AxisY": {
                    "X": 0.0,
                    "Y": 1.0,
                    "Z": 0.0
                  },
                  "AxisZ": {
                    "X": 0.0,
                    "Y": 0.0,
                    "Z": -1.0
                  },
                  "Origin": {
                    "X": -3.0107422,
                    "Y": -7.471756,
                    "Z": 5.422323
                  },
                  "Extent": {
                    "X": 140.0,
                    "Y": 159.50153,
                    "Z": 25.0
                  }
                },
                "LODLevel": 0,
                "AxisAlignedDirectionIndex": 4
              },
              {
                "OBB": {
                  "AxisX": {
                    "X": 1.0,
                    "Y": 0.0,
                    "Z": 0.0
                  },
                  "AxisY": {
                    "X": 0.0,
                    "Y": 1.0,
                    "Z": 0.0
                  },
                  "AxisZ": {
                    "X": 0.0,
                    "Y": 0.0,
                    "Z": 1.0
                  },
                  "Origin": {
                    "X": -3.0107422,
                    "Y": -7.471756,
                    "Z": 20.422325
                  },
                  "Extent": {
                    "X": 140.0,
                    "Y": 159.50153,
                    "Z": 20.0
                  }
                },
                "LODLevel": 0,
                "AxisAlignedDirectionIndex": 5
              }
            ]
          }
        },
        {
          "Sections": [
            {
              "MaterialIndex": 0,
              "FirstIndex": 0,
              "NumTriangles": 198,
              "MinVertexIndex": 0,
              "MaxVertexIndex": 593,
              "bEnableCollision": true,
              "bCastShadow": true,
              "bForceOpaque": false,
              "bVisibleInRayTracing": true
            }
          ],
          "MaxDeviation": 686.61237,
          "PositionVertexBuffer": {
            "Stride": 12,
            "NumVertices": 594
          },
          "VertexBuffer": {
            "NumTexCoords": 2,
            "NumVertices": 594,
            "Strides": -1,
            "UseHighPrecisionTangentBasis": false,
            "UseFullPrecisionUVs": false
          },
          "ColorVertexBuffer": {
            "Stride": 0,
            "NumVertices": 0
          }
        },
        {
          "Sections": [
            {
              "MaterialIndex": 0,
              "FirstIndex": 0,
              "NumTriangles": 86,
              "MinVertexIndex": 0,
              "MaxVertexIndex": 257,
              "bEnableCollision": true,
              "bCastShadow": true,
              "bForceOpaque": false,
              "bVisibleInRayTracing": true
            }
          ],
          "MaxDeviation": 1783.4309,
          "PositionVertexBuffer": {
            "Stride": 12,
            "NumVertices": 258
          },
          "VertexBuffer": {
            "NumTexCoords": 2,
            "NumVertices": 258,
            "Strides": -1,
            "UseHighPrecisionTangentBasis": false,
            "UseFullPrecisionUVs": false
          },
          "ColorVertexBuffer": {
            "Stride": 0,
            "NumVertices": 0
          }
        }
      ],
      "NaniteResources": {
        "RootData": null,
        "StreamablePages": {
          "BulkDataFlags": "BULKDATA_None",
          "ElementCount": 0,
          "SizeOnDisk": 0,
          "OffsetInFile": "0x34CA6"
        },
        "ImposterAtlas": [],
        "HierarchyNodes": [],
        "HierarchyRootOffsets": [],
        "PageStreamingStates": [],
        "PageDependencies": [],
        "NumRootPages": 0,
        "PositionPrecision": 0,
        "NormalPrecision": 0,
        "TangentPrecision": 0,
        "NumInputTriangles": 0,
        "NumInputVertices": 0,
        "NumInputMeshes": 0,
        "NumInputTexCoords": 0,
        "NumClusters": 0,
        "ResourceFlags": 0
      },
      "Bounds": {
        "Origin": {
          "X": -3.0107422,
          "Y": -7.471756,
          "Z": 10.422323
        },
        "BoxExtent": {
          "X": 139.60449,
          "Y": 158.50154,
          "Z": 21.718954
        },
        "SphereRadius": 175.46992
      },
      "bLODsShareStaticLighting": false,
      "ScreenSize": [
        1.0,
        0.3,
        0.06,
        0.0,
        0.0,
        0.0,
        0.0,
        0.0
      ]
    }
  }
]