[
  {
    "Type": "MaterialInstanceConstant",
    "Name": "MI_UI_EffectAttentionSmoke_02",
    "Class": "UScriptClass'MaterialInstanceConstant'",
    "Properties": {
      "Parent": {
        "ObjectName": "Material'M_UI_EffectAttentionSmoke'",
        "ObjectPath": "Pal/Content/Pal/Material/UI/Ingame/M_UI_EffectAttentionSmoke.0"
      },
      "ScalarParameterValues": [
        {
          "ParameterInfo": {
            "Name": "Amount",
            "Association": "EMaterialParameterAssociation::GlobalParameter",
            "Index": -1
          },
          "ParameterValue": 0.162,
          "ExpressionGUID": "699FC359-45D59EE8-2C9CB59C-486DC408"
        },
        {
          "ParameterInfo": {
            "Name": "Speed0",
            "Association": "EMaterialParameterAssociation::GlobalParameter",
            "Index": -1
          },
          "ParameterValue": 0.224,
          "ExpressionGUID": "DC30419D-4C3EC7F3-0A06BC8E-F261460A"
        },
        {
          "ParameterInfo": {
            "Name": "Speed1",
            "Association": "EMaterialParameterAssociation::GlobalParameter",
            "Index": -1
          },
          "ParameterValue": -0.496,
          "ExpressionGUID": "38DC207C-4E7BEFC8-D6D78CA6-97809167"
        },
        {
          "ParameterInfo": {
            "Name": "RefractionDepthBias",
            "Association": "EMaterialParameterAssociation::GlobalParameter",
            "Index": -1
          },
          "ParameterValue": 0.0,
          "ExpressionGUID": "00000000-00000000-00000000-00000000"
        }
      ],
      "BasePropertyOverrides": {
        "BlendMode": "EBlendMode::BLEND_Additive",
        "ShadingModel": "EMaterialShadingModel::MSM_Unlit",
        "OpacityMaskClipValue": 0.3333
      }
    },
    "CachedData": {
      "ParentLayerIndexRemap": []
    }
  }
]