[
  {
    "Type": "BodySetup",
    "Name": "BodySetup_0",
    "Outer": "Banyan_Hero_Forest_A",
    "Class": "UScriptClass'BodySetup'",
    "Properties": {
      "AggGeom": {
        "SphylElems": [
          {
            "Center": {
              "X": -6.058556,
              "Y": -0.4821486,
              "Z": 120.8226
            },
            "Rotation": {
              "Pitch": -0.0,
              "Yaw": 0.0,
              "Roll": 1.6522963
            },
            "Radius": 39.654694,
            "Length": 266.86972,
            "RestOffset": 0.0,
            "Name": "None",
            "bContributeToMass": true,
            "CollisionEnabled": "ECollisionEnabled::QueryAndPhysics"
          }
        ]
      },
      "DefaultInstance": {
        "ObjectType": "ECollisionChannel::ECC_WorldStatic",
        "CollisionProfileName": "Background",
        "CollisionResponses": {
          "ResponseArray": [
            {
              "Channel": "Attack",
              "Response": "ECollisionResponse::ECR_Block"
            },
            {
              "Channel": "SystemVolume",
              "Response": "ECollisionResponse::ECR_Ignore"
            },
            {
              "Channel": "LiftedupPawn",
              "Response": "ECollisionResponse::ECR_Block"
            },
            {
              "Channel": "AISightRayCast",
              "Response": "ECollisionResponse::ECR_Block"
            },
            {
              "Channel": "vsGroundRayCast",
              "Response": "ECollisionResponse::ECR_Block"
            },
            {
              "Channel": "ClimbRayCast",
              "Response": "ECollisionResponse::ECR_Block"
            },
            {
              "Channel": "RollingRayCast",
              "Response": "ECollisionResponse::ECR_Block"
            }
          ]
        }
      }
    },
    "BodySetupGuid": "A1F9932E417EF41695C8A9921804BB8B",
    "CookedFormatData": {
      "PhysXPC": {
        "BulkDataFlags": "BULKDATA_SingleUse | BULKDATA_ForceInlinePayload",
        "ElementCount": 2294022,
        "SizeOnDisk": 2294022,
        "OffsetInFile": "0x39C4A8"
      }
    }
  },
  {
    "Type": "NavCollision",
    "Name": "NavCollision_0",
    "Outer": "Banyan_Hero_Forest_A",
    "Class": "UScriptClass'NavCollision'",
    "CookedFormatData": {
      "NavCollision_Chaos": {
        "BulkDataFlags": "BULKDATA_SingleUse | BULKDATA_ForceInlinePayload",
        "ElementCount": 7561,
        "SizeOnDisk": 7561,
        "OffsetInFile": "0x5CC5F0"
      }
    }
  },
  {
    "Type": "StaticMesh",
    "Name": "Banyan_Hero_Forest_A",
    "Class": "UScriptClass'StaticMesh'",
    "Properties": {
      "StaticMaterials": [
        {
          "MaterialInterface": {
            "ObjectName": "MaterialInstanceConstant'MI_PalLit_Banyan_TreeTrunk'",
            "ObjectPath": "Pal/Content/Pal/Model/Stage/tree/b00/SpeedTree/Material/MI_PalLit_Banyan_TreeTrunk.0"
          },
          "MaterialSlotName": "Banyan_Bark_1_Branch_Mat",
          "ImportedMaterialSlotName": "Banyan_Bark_1_Branch_Mat",
          "UVChannelData": {
            "bInitialized": true,
            "bOverrideDensities": false,
            "LocalUVDensities": 56.59283,
            "LocalUVDensities": 650.5468,
            "LocalUVDensities": 0.0,
            "LocalUVDensities": 2.028233
          }
        },
        {
          "MaterialInterface": {
            "ObjectName": "MaterialInstanceConstant'MI_PalLit_Banyan_Leaves'",
            "ObjectPath": "Pal/Content/Pal/Model/Stage/tree/b00/SpeedTree/Material/MI_PalLit_Banyan_Leaves.0"
          },
          "MaterialSlotName": "Banyan_Hero_Forest_A_Leaf_Mat",
          "ImportedMaterialSlotName": "Banyan_Hero_Forest_A_Leaf_Mat",
          "UVChannelData": {
            "bInitialized": true,
            "bOverrideDensities": false,
            "LocalUVDensities": 293.71753,
            "LocalUVDensities": 18759.61,
            "LocalUVDensities": 0.0,
            "LocalUVDensities": 1.4991843
          }
        },
        {
          "MaterialInterface": {
            "ObjectName": "MaterialInstanceConstant'MI_Impostor80'",
            "ObjectPath": "Pal/Content/Pal/Model/Stage/tree/b00/SpeedTree/Mesh/Banyan/material/MI_Impostor80.0"
          },
          "MaterialSlotName": "MaterialInstanceDynamic_14",
          "ImportedMaterialSlotName": "MaterialInstanceDynamic_14",
          "UVChannelData": {
            "bInitialized": true,
            "bOverrideDensities": false,
            "LocalUVDensities": 0.0,
            "LocalUVDensities": 0.0,
            "LocalUVDensities": 0.0,
            "LocalUVDensities": 0.0
          }
        }
      ],
      "LightmapUVDensity": 15925.734,
      "LightMapResolution": 128,
      "LightMapCoordinateIndex": 1,
      "ExtendedBounds": {
        "Origin": {
          "X": -47.58278,
          "Y": 39.743713,
          "Z": 210.92236
        },
        "BoxExtent": {
          "X": 306.02356,
          "Y": 316.91373,
          "Z": 295.21643
        },
        "SphereRadius": 457.6950529160663
      }
    },
    "BodySetup": {
      "ObjectName": "BodySetup'Banyan_Hero_Forest_A:BodySetup_0'",
      "ObjectPath": "Pal/Content/Pal/Model/Stage/tree/b00/SpeedTree/Mesh/Banyan/Banyan_Hero_Forest_A.0"
    },
    "NavCollision": {
      "ObjectName": "NavCollision'Banyan_Hero_Forest_A:NavCollision_0'",
      "ObjectPath": "Pal/Content/Pal/Model/Stage/tree/b00/SpeedTree/Mesh/Banyan/Banyan_Hero_Forest_A.1"
    },
    "LightingGuid": "3260902A-43C4D546-D35C1F92-104F3226",
    "RenderData": {
      "LODs": [
        {
          "Sections": [
            {
              "MaterialIndex": 0,
              "FirstIndex": 0,
              "NumTriangles": 4401,
              "MinVertexIndex": 0,
              "MaxVertexIndex": 2755,
              "bEnableCollision": true,
              "bCastShadow": true,
              "bForceOpaque": false,
              "bVisibleInRayTracing": true
            },
            {
              "MaterialIndex": 1,
              "FirstIndex": 13203,
              "NumTriangles": 7609,
              "MinVertexIndex": 2756,
              "MaxVertexIndex": 9950,
              "bEnableCollision": true,
              "bCastShadow": true,
              "bForceOpaque": false,
              "bVisibleInRayTracing": true
            }
          ],
          "MaxDeviation": 0.0,
          "PositionVertexBuffer": {
            "Stride": 12,
            "NumVertices": 9951
          },
          "VertexBuffer": {
            "NumTexCoords": 8,
            "NumVertices": 9951,
            "Strides": -1,
            "UseHighPrecisionTangentBasis": false,
            "UseFullPrecisionUVs": false
          },
          "ColorVertexBuffer": {
            "Stride": 4,
            "NumVertices": 9951
          },
          "CardRepresentationData": {
            "Bounds": {
              "Min": {
                "X": -359.7496,
                "Y": -283.20038,
                "Z": -90.25569
              },
              "Max": {
                "X": 264.58405,
                "Y": 362.6878,
                "Z": 512.1004
              },
              "IsValid": 1
            },
            "MaxLodLevel": 0,
            "bMostlyTwoSided": false,
            "CardBuildData": [
              {
                "OBB": {
                  "AxisX": {
                    "X": 0.0,
                    "Y": 1.0,
                    "Z": 0.0
                  },
                  "AxisY": {
                    "X": 0.0,
                    "Y": 0.0,
                    "Z": 1.0
                  },
                  "AxisZ": {
                    "X": -1.0,
                    "Y": 0.0,
                    "Z": 0.0
                  },
                  "Origin": {
                    "X": -47.582764,
                    "Y": 39.743713,
                    "Z": 210.92236
                  },
                  "Extent": {
                    "X": 322.9441,
                    "Y": 301.17804,
                    "Z": 322.1668
                  }
                },
                "LODLevel": 0,
                "AxisAlignedDirectionIndex": 0
              },
              {
                "OBB": {
                  "AxisX": {
                    "X": 0.0,
                    "Y": 1.0,
                    "Z": 0.0
                  },
                  "AxisY": {
                    "X": 0.0,
                    "Y": 0.0,
                    "Z": 1.0
                  },
                  "AxisZ": {
                    "X": 1.0,
                    "Y": 0.0,
                    "Z": 0.0
                  },
                  "Origin": {
                    "X": -27.78743,
                    "Y": 39.743713,
                    "Z": 210.92236
                  },
                  "Extent": {
                    "X": 322.9441,
                    "Y": 301.17804,
                    "Z": 302.37146
                  }
                },
                "LODLevel": 0,
                "AxisAlignedDirectionIndex": 1
              },
              {
                "OBB": {
                  "AxisX": {
                    "X": 1.0,
                    "Y": 0.0,
                    "Z": 0.0
                  },
                  "AxisY": {
                    "X": 0.0,
                    "Y": 0.0,
                    "Z": 1.0
                  },
                  "AxisZ": {
                    "X": 0.0,
                    "Y": -1.0,
                    "Z": 0.0
                  },
                  "Origin": {
                    "X": -47.582764,
                    "Y": 39.743713,
                    "Z": 210.92236
                  },
                  "Extent": {
                    "X": 302.76007,
                    "Y": 301.17804,
                    "Z": 332.9441
                  }
                },
                "LODLevel": 0,
                "AxisAlignedDirectionIndex": 2
              },
              {
                "OBB": {
                  "AxisX": {
                    "X": 1.0,
                    "Y": 0.0,
                    "Z": 0.0
                  },
                  "AxisY": {
                    "X": 0.0,
                    "Y": 0.0,
                    "Z": 1.0
                  },
                  "AxisZ": {
                    "X": 0.0,
                    "Y": 1.0,
                    "Z": 0.0
                  },
                  "Origin": {
                    "X": -47.582764,
                    "Y": 75.019714,
                    "Z": 210.92236
                  },
                  "Extent": {
                    "X": 302.76007,
                    "Y": 301.17804,
                    "Z": 297.6681
                  }
                },
                "LODLevel": 0,
                "AxisAlignedDirectionIndex": 3
              },
              {
                "OBB": {
                  "AxisX": {
                    "X": 1.0,
                    "Y": 0.0,
                    "Z": 0.0
                  },
                  "AxisY": {
                    "X": 0.0,
                    "Y": 1.0,
                    "Z": 0.0
                  },
                  "AxisZ": {
                    "X": 0.0,
                    "Y": 0.0,
                    "Z": -1.0
                  },
                  "Origin": {
                    "X": -47.582764,
                    "Y": 39.743713,
                    "Z": 196.6214
                  },
                  "Extent": {
                    "X": 302.76007,
                    "Y": 322.9441,
                    "Z": 296.87708
                  }
                },
                "LODLevel": 0,
                "AxisAlignedDirectionIndex": 4
              },
              {
                "OBB": {
                  "AxisX": {
                    "X": 1.0,
                    "Y": 0.0,
                    "Z": 0.0
                  },
                  "AxisY": {
                    "X": 0.0,
                    "Y": 1.0,
                    "Z": 0.0
                  },
                  "AxisZ": {
                    "X": 0.0,
                    "Y": 0.0,
                    "Z": 1.0
                  },
                  "Origin": {
                    "X": -47.582764,
                    "Y": 39.743713,
                    "Z": 225.22333
                  },
                  "Extent": {
                    "X": 302.76007,
                    "Y": 322.9441,
                    "Z": 296.87708
                  }
                },
                "LODLevel": 0,
                "AxisAlignedDirectionIndex": 5
              }
            ]
          }
        },
        {
          "Sections": [
            {
              "MaterialIndex": 0,
              "FirstIndex": 0,
              "NumTriangles": 3342,
              "MinVertexIndex": 0,
              "MaxVertexIndex": 1981,
              "bEnableCollision": true,
              "bCastShadow": true,
              "bForceOpaque": false,
              "bVisibleInRayTracing": true
            },
            {
              "MaterialIndex": 1,
              "FirstIndex": 10026,
              "NumTriangles": 3096,
              "MinVertexIndex": 1982,
              "MaxVertexIndex": 5163,
              "bEnableCollision": true,
              "bCastShadow": true,
              "bForceOpaque": false,
              "bVisibleInRayTracing": true
            }
          ],
          "MaxDeviation": 0.0,
          "PositionVertexBuffer": {
            "Stride": 12,
            "NumVertices": 5164
          },
          "VertexBuffer": {
            "NumTexCoords": 8,
            "NumVertices": 5164,
            "Strides": -1,
            "UseHighPrecisionTangentBasis": false,
            "UseFullPrecisionUVs": false
          },
          "ColorVertexBuffer": {
            "Stride": 4,
            "NumVertices": 5164
          }
        },
        {
          "Sections": [
            {
              "MaterialIndex": 0,
              "FirstIndex": 0,
              "NumTriangles": 880,
              "MinVertexIndex": 0,
              "MaxVertexIndex": 523,
              "bEnableCollision": true,
              "bCastShadow": true,
              "bForceOpaque": false,
              "bVisibleInRayTracing": true
            },
            {
              "MaterialIndex": 1,
              "FirstIndex": 2640,
              "NumTriangles": 825,
              "MinVertexIndex": 524,
              "MaxVertexIndex": 1434,
              "bEnableCollision": true,
              "bCastShadow": true,
              "bForceOpaque": false,
              "bVisibleInRayTracing": true
            }
          ],
          "MaxDeviation": 0.0,
          "PositionVertexBuffer": {
            "Stride": 12,
            "NumVertices": 1435
          },
          "VertexBuffer": {
            "NumTexCoords": 8,
            "NumVertices": 1435,
            "Strides": -1,
            "UseHighPrecisionTangentBasis": false,
            "UseFullPrecisionUVs": false
          },
          "ColorVertexBuffer": {
            "Stride": 4,
            "NumVertices": 1435
          }
        },
        {
          "Sections": [
            {
              "MaterialIndex": 2,
              "FirstIndex": 0,
              "NumTriangles": 8,
              "MinVertexIndex": 0,
              "MaxVertexIndex": 8,
              "bEnableCollision": true,
              "bCastShadow": true,
              "bForceOpaque": false,
              "bVisibleInRayTracing": true
            }
          ],
          "MaxDeviation": 0.0,
          "PositionVertexBuffer": {
            "Stride": 12,
            "NumVertices": 9
          },
          "VertexBuffer": {
            "NumTexCoords": 8,
            "NumVertices": 9,
            "Strides": -1,
            "UseHighPrecisionTangentBasis": false,
            "UseFullPrecisionUVs": false
          },
          "ColorVertexBuffer": {
            "Stride": 0,
            "NumVertices": 0
          }
        }
      ],
      "NaniteResources": {
        "RootData": null,
        "StreamablePages": {
          "BulkDataFlags": "BULKDATA_None",
          "ElementCount": 0,
          "SizeOnDisk": 0,
          "OffsetInFile": "0x7270D6"
        },
        "ImposterAtlas": [],
        "HierarchyNodes": [],
        "HierarchyRootOffsets": [],
        "PageStreamingStates": [],
        "PageDependencies": [],
        "NumRootPages": 0,
        "PositionPrecision": 0,
        "NormalPrecision": 0,
        "TangentPrecision": 0,
        "NumInputTriangles": 0,
        "NumInputVertices": 0,
        "NumInputMeshes": 0,
        "NumInputTexCoords": 0,
        "NumClusters": 0,
        "ResourceFlags": 0
      },
      "Bounds": {
        "Origin": {
          "X": -47.58278,
          "Y": 39.743713,
          "Z": 210.92236
        },
        "BoxExtent": {
          "X": 306.02356,
          "Y": 316.91373,
          "Z": 295.21643
        },
        "SphereRadius": 457.69507
      },
      "bLODsShareStaticLighting": true,
      "ScreenSize": [
        1.0,
        0.9,
        0.6,
        0.100000024,
        0.0,
        0.0,
        0.0,
        0.0
      ]
    }
  }
]